laflem/__init__.py
laflem/flem.py
laflem/log.py
laflem/collections/__init__.py
laflem/collections/base/__init__.py
laflem/collections/base/ask.py
laflem/collections/base/helloworld.py
laflem/collections/git/__init__.py
laflem/collections/git/const.py
laflem/collections/git/setup.py
laflem/collections/macos/__init__.py
laflem/collections/macos/homebrew/__init__.py
laflem/collections/macos/homebrew/cleanup.py
laflem/collections/macos/homebrew/const.py
laflem/collections/macos/homebrew/setup.py
laflem/collections/macos/homebrew/upgrade.py
laflem/collections/python/__init__.py
laflem/collections/python/virtualenv/__init__.py
laflem/collections/python/virtualenv/cleanup.py
laflem/collections/python/virtualenv/const.py
laflem/collections/python/virtualenv/create.py
laflem/collections/python/virtualenv/delete.py
laflem/collections/python/virtualenv/list.py
laflem/collections/self/__init__.py
laflem/collections/self/const.py
laflem/collections/self/upgrade.py
laflem/exceptions/__init__.py
laflem/exceptions/base.py
laflem/exceptions/collections.py
laflem/exceptions/http.py
laflem/exceptions/modules.py
laflem/tools/__init__.py
laflem/tools/requirements.py
laflem-0.4.0.data/data/configs/laflem/base.yml
laflem-0.4.0.dist-info/LICENSE
laflem-0.4.0.dist-info/METADATA
laflem-0.4.0.dist-info/WHEEL
laflem-0.4.0.dist-info/entry_points.txt
laflem-0.4.0.dist-info/top_level.txt
laflem-0.4.0.dist-info/RECORD
