Metadata-Version: 2.1
Name: laflem
Version: 0.4.0
Summary: Tools collection
Home-page: https://github.com/Lunik/laflem
Download-URL: https://pypi.org/project/laflem/
Author: Guillaume MARTINEZ
Author-email: lunik@tiwabbit.fr
Maintainer: Guillaume MARTINEZ
Maintainer-email: lunik@tiwabbit.fr
Classifier: Development Status :: 3 - Alpha
Classifier: Intended Audience :: Developers
Classifier: Intended Audience :: Information Technology
Classifier: Intended Audience :: System Administrators
Classifier: Topic :: Software Development :: Build Tools
Classifier: License :: OSI Approved :: GNU General Public License v3 (GPLv3)
Classifier: Programming Language :: Python :: 3
Classifier: Programming Language :: Python :: 3.8
Classifier: Programming Language :: Python :: 3.9
Classifier: Programming Language :: Python :: 3.10
Classifier: Programming Language :: Python :: 3.11
Requires-Python: >=3.8.0
License-File: LICENSE
Requires-Dist: rich ==13.*
Requires-Dist: importlib-metadata ==6.*
Requires-Dist: requests ==2.*
Provides-Extra: dev
Requires-Dist: pylint ; extra == 'dev'
Requires-Dist: black ; extra == 'dev'
Requires-Dist: twine ; extra == 'dev'
Requires-Dist: build ; extra == 'dev'
Requires-Dist: pytest ; extra == 'dev'
Requires-Dist: pytest-cov ; extra == 'dev'
Requires-Dist: pytest-html ; extra == 'dev'
Requires-Dist: pytest-xdist ; extra == 'dev'
Requires-Dist: pytest-helpers-namespace ; extra == 'dev'
Requires-Dist: pytest-order ; extra == 'dev'
Requires-Dist: wheel ; extra == 'dev'
Provides-Extra: git
Requires-Dist: gitpython ==3.* ; extra == 'git'
